src/__init__.py
src/cli.py
src/commands/__init__.py
src/commands/check_deps.py
src/commands/create.py
src/commands/delete.py
src/commands/list_agents.py
src/commands/publish.py
src/commands/run.py
src/converters/__init__.py
src/converters/flow_converter.py
src/mappings/__init__.py
src/models/__init__.py
src/models/agent_spec_enhanced.py
src/models/component_provides.py
src/parsers/__init__.py
src/parsers/enhanced_spec_parser.py
src/registry/__init__.py
src/registry/dynamic_component_mapper.py
src/services/__init__.py
src/services/component_loader.py
src/services/config.py
src/services/container_builder.py
src/services/genesis_studio_api.py
src/services/variable_resolver.py
genesis_agent_cli-0.1.0.dist-info/METADATA
genesis_agent_cli-0.1.0.dist-info/WHEEL
genesis_agent_cli-0.1.0.dist-info/entry_points.txt
genesis_agent_cli-0.1.0.dist-info/RECORD
