Metadata-Version: 2.4
Name: genesis-agent-cli
Version: 0.1.0
Summary: CLI tool for managing AI agents in Genesis-Studio using Agent Specifications
Author: Genesis Platform Team
Requires-Python: >=3.10
Requires-Dist: click>=8.1.7
Requires-Dist: docker>=7.0.0
Requires-Dist: httpx>=0.27.0
Requires-Dist: jinja2>=3.1.3
Requires-Dist: pydantic>=2.6.0
Requires-Dist: pyyaml>=6.0.1
Requires-Dist: rich>=13.7.1
Provides-Extra: dev
Requires-Dist: mypy>=1.8.0; extra == 'dev'
Requires-Dist: pytest-asyncio>=0.23.0; extra == 'dev'
Requires-Dist: pytest-httpx>=0.30.0; extra == 'dev'
Requires-Dist: pytest>=8.0.0; extra == 'dev'
Requires-Dist: ruff>=0.2.0; extra == 'dev'
